MANIFEST.in
README.rst
requirements-dev.txt
requirements.txt
setup.cfg
setup.py
stockscore/__init__.py
stockscore/data.py
stockscore/graph.py
stockscore/scores.py
stockscore.egg-info/PKG-INFO
stockscore.egg-info/SOURCES.txt
stockscore.egg-info/dependency_links.txt
stockscore.egg-info/requires.txt
stockscore.egg-info/top_level.txt
stockscore/tests/__init__.py
stockscore/tests/conftest.py
stockscore/tests/test_data.py
stockscore/tests/test_scores.py