Metadata-Version: 2.1
Name: stockscore
Version: 0.4.2
Summary: UNKNOWN
Home-page: https://github.com/jackmoody11/stockscore
Author: Jack Moody
License: MIT
Download-URL: https://github.com/jackmoody11/stockscore/releases
Keywords: stocks market finance
Platform: UNKNOWN
Classifier: Development Status :: 3 - Alpha
Classifier: Intended Audience :: Developers
Classifier: Intended Audience :: Financial and Insurance Industry
Classifier: Topic :: Office/Business :: Financial :: Investment
Classifier: Topic :: Software Development :: Libraries :: Python Modules
Classifier: Operating System :: OS Independent
Classifier: License :: OSI Approved :: MIT License
Classifier: Programming Language :: Python
Classifier: Programming Language :: Python :: 3
Classifier: Programming Language :: Python :: 3.5
Classifier: Programming Language :: Python :: 3.6
Classifier: Programming Language :: Python :: 3.7
